{
  "db_name": "PostgreSQL",
  "query": "\n        SELECT id, court_id, docket_entry_id, filename, file_size, content_type,\n               storage_key, sealed, encryption, sha256, uploaded_at, created_at, updated_at\n        FROM docket_attachments\n        WHERE id = $1 AND court_id = $2\n        ",
  "describe": {
    "columns": [
      {
        "ordinal": 0,
        "name": "id",
        "type_info": "Uuid"
      },
      {
        "ordinal": 1,
        "name": "court_id",
        "type_info": "Text"
      },
      {
        "ordinal": 2,
        "name": "docket_entry_id",
        "type_info": "Uuid"
      },
      {
        "ordinal": 3,
        "name": "filename",
        "type_info": "Text"
      },
      {
        "ordinal": 4,
        "name": "file_size",
        "type_info": "Int8"
      },
      {
        "ordinal": 5,
        "name": "content_type",
        "type_info": "Text"
      },
      {
        "ordinal": 6,
        "name": "storage_key",
        "type_info": "Text"
      },
      {
        "ordinal": 7,
        "name": "sealed",
        "type_info": "Bool"
      },
      {
        "ordinal": 8,
        "name": "encryption",
        "type_info": "Text"
      },
      {
        "ordinal": 9,
        "name": "sha256",
        "type_info": "Text"
      },
      {
        "ordinal": 10,
        "name": "uploaded_at",
        "type_info": "Timestamptz"
      },
      {
        "ordinal": 11,
        "name": "created_at",
        "type_info": "Timestamptz"
      },
      {
        "ordinal": 12,
        "name": "updated_at",
        "type_info": "Timestamptz"
      }
    ],
    "parameters": {
      "Left": [
        "Uuid",
        "Text"
      ]
    },
    "nullable": [
      false,
      false,
      false,
      false,
      false,
      false,
      false,
      false,
      false,
      true,
      true,
      false,
      false
    ]
  },
  "hash": "14617b1dad21093866e7bd55df501b3efb5054b560b278147790f42b53833c37"
}
